setup.py
django_simple_aes_field/__init__.py
django_simple_aes_field/fields.py
django_simple_aes_field.egg-info/PKG-INFO
django_simple_aes_field.egg-info/SOURCES.txt
django_simple_aes_field.egg-info/dependency_links.txt
django_simple_aes_field.egg-info/requires.txt
django_simple_aes_field.egg-info/top_level.txt