Metadata-Version: 1.0
Name: django-simple-aes-field
Version: 0.1.3
Summary: A SimpleAES encoded field for Django.
Home-page: http://incuna.com/
Author: Incuna Ltd
Author-email: dev@incuna.com
License: UNKNOWN
Platform: UNKNOWN
